{
  "version": "1.2.0",
  "lastUpdated": "2026-02-10T00:00:00Z",
  "games": [
    {
      "id": "slots",
      "title": "Lucky Slots",
      "description": "A relaxing slot machine game with smooth animations.",
      "path": "/slots/",
      "external": true,
      "iconSvg": "/icons/slots.svg",
      "gradient": ["#1a5a4a", "#0d3d33"],
      "order": 1
    },
    {
      "id": "blackjack",
      "title": "Blackjack",
      "description": "Friendly casino classic. Beat the dealer to 21!",
      "path": "/blackjack/",
      "external": true,
      "iconSvg": "/icons/blackjack.svg",
      "gradient": ["#1a5a4a", "#0d3d33"],
      "order": 2
    },
    {
      "id": "roulette",
      "title": "Roulette",
      "description": "Spin the wheel and test your luck!",
      "path": "/roulette/",
      "external": true,
      "iconSvg": "/icons/roulette.svg",
      "gradient": ["#1a5a4a", "#0d3d33"],
      "order": 3
    },
    {
      "id": "poker",
      "title": "Video Poker",
      "description": "Classic Jacks or Better video poker.",
      "path": "/poker/",
      "external": true,
      "iconSvg": "/icons/poker.svg",
      "gradient": ["#1a5a4a", "#0d3d33"],
      "order": 4
    },
    {
      "id": "holdem",
      "title": "Texas Hold'em",
      "description": "Play poker against two friendly AI opponents!",
      "path": "/holdem/",
      "external": true,
      "iconSvg": "/icons/poker.svg",
      "gradient": ["#1a5a4a", "#0d3d33"],
      "order": 5
    },
    {
      "id": "craps",
      "title": "Craps",
      "description": "Roll the dice in this classic casino game.",
      "path": "/craps/",
      "external": true,
      "iconSvg": "/icons/craps.svg",
      "gradient": ["#1a5a4a", "#0d3d33"],
      "order": 6
    },
    {
      "id": "wordchange",
      "title": "Word Change",
      "description": "Change one letter to make a new word!",
      "path": "/wordchange/",
      "external": true,
      "iconSvg": "/icons/wordchange.svg",
      "gradient": ["#1a5a4a", "#0d3d33"],
      "order": 7
    },
    {
      "id": "solitaire",
      "title": "Solitaire",
      "description": "Relaxing Klondike solitaire with hints and undo.",
      "path": "/solitaire/",
      "external": true,
      "iconSvg": "/icons/solitaire.svg",
      "gradient": ["#1a5a4a", "#0d3d33"],
      "order": 8
    },
    {
      "id": "checkers",
      "title": "Checkers",
      "description": "Classic checkers with tap/drag moves and gentle hints.",
      "path": "/checkers/",
      "external": true,
      "iconSvg": "/icons/checkers.svg",
      "gradient": ["#1a5a4a", "#0d3d33"],
      "order": 9
    }
  ]
}
